ml_lib_remla/__init__.py
ml_lib_remla/preprocessing.py
resources/label_encoder.pkl
resources/tokenizer.pkl
ml_lib_remla-1.1.4.dist-info/METADATA
ml_lib_remla-1.1.4.dist-info/WHEEL
ml_lib_remla-1.1.4.dist-info/RECORD
