Metadata-Version: 2.1
Name: ml-lib-remla
Version: 1.1.4
Summary: 
Author: oltremare
Author-email: oncwnuHZnY0Uo1jEvpEs9s-sZa78@git.weixin.qq.com
Requires-Python: >=3.11,<4.0
Classifier: Programming Language :: Python :: 3
Classifier: Programming Language :: Python :: 3.11
Classifier: Programming Language :: Python :: 3.12
Requires-Dist: importlib-resources (>=6.4.0,<7.0.0)
Requires-Dist: numpy (>=1.26.4,<2.0.0)
Requires-Dist: scikit-learn (>=1.4.2,<2.0.0)
Requires-Dist: transformers (>=4.41.2,<5.0.0)
